skorfmann_cdktf_provider_aws/__init__.py
skorfmann_cdktf_provider_aws/py.typed
skorfmann_cdktf_provider_aws/_jsii/__init__.py
skorfmann_cdktf_provider_aws/_jsii/cdktf-provider-aws@0.0.14.jsii.tgz
skorfmann_cdktf_provider_aws-0.0.14.dist-info/METADATA
skorfmann_cdktf_provider_aws-0.0.14.dist-info/WHEEL
skorfmann_cdktf_provider_aws-0.0.14.dist-info/top_level.txt
skorfmann_cdktf_provider_aws-0.0.14.dist-info/RECORD
