Metadata-Version: 2.1
Name: skorfmann-cdktf-provider-aws
Version: 0.0.14
Summary: Prebuilt AWS Provider for Terraform CDK (cdktf)
Home-page: https://github.com/skorfmann/cdktf-provider-aws.git
Author: Sebastian Korfmann<sebastian@korfmann.net>
License: MPL-2.0
Project-URL: Source, https://github.com/skorfmann/cdktf-provider-aws.git
Platform: UNKNOWN
Classifier: Intended Audience :: Developers
Classifier: Operating System :: OS Independent
Classifier: Programming Language :: JavaScript
Classifier: Programming Language :: Python :: 3 :: Only
Classifier: Programming Language :: Python :: 3.6
Classifier: Programming Language :: Python :: 3.7
Classifier: Programming Language :: Python :: 3.8
Classifier: Typing :: Typed
Classifier: Development Status :: 5 - Production/Stable
Classifier: License :: OSI Approved
Requires-Python: >=3.6
Requires-Dist: jsii (<2.0.0,>=1.10.0)
Requires-Dist: publication (>=0.0.3)
Requires-Dist: cdktf (<0.0.15,>=0.0.14)
Requires-Dist: constructs (<4.0.0,>=3.0.4)
